[{"line":1,"elements":[{"start_timestamp":"2023-04-13T01:43:46.427Z","before":[{"result":{"duration":8895308000,"status":"passed"},"match":{"location":"StepDefinitions.Hooks.preCondition()"}}],"line":4,"name":"Adding a new Employee","description":"","id":"employee;adding-a-new-employee","after":[{"result":{"duration":242775000,"status":"passed"},"match":{"location":"StepDefinitions.Hooks.postCondition()"}}],"type":"scenario","keyword":"Scenario","steps":[{"result":{"duration":501726000,"status":"passed"},"line":6,"name":"user enters valid email and valid password","match":{"location":"StepDefinitions.Login.user_enters_valid_email_and_valid_password()"},"keyword":"When "},{"result":{"duration":1697918000,"status":"passed"},"line":7,"name":"click on login button","match":{"location":"StepDefinitions.Login.click_on_login_button()"},"keyword":"And "},{"result":{"duration":12315126000,"status":"passed"},"line":8,"name":"user clicks on PIM option","match":{"location":"StepDefinitions.AddEmployee.user_clicks_on_pim_option()"},"keyword":"When "},{"result":{"duration":1949810000,"status":"passed"},"line":9,"name":"user clicks on add employee button","match":{"location":"StepDefinitions.AddEmployee.user_clicks_on_add_employee_button()"},"keyword":"And "},{"result":{"duration":302171000,"status":"passed"},"line":10,"name":"user enters firstname and middlename and lastname","match":{"location":"StepDefinitions.AddEmployee.user_enters_firstname_and_middlename_and_lastname()"},"keyword":"And "}],"tags":[{"name":"@testcase2"}]}],"name":"Employee","description":"","id":"employee","keyword":"Feature","uri":"file:src/test/resources/Features/AddEmployee.feature","tags":[]}]